puck_bridge_py/__init__.py
puck_bridge_py/commands.py
puck_bridge_py/event_system.py
puck_bridge_py/game_state.py
puck_bridge_py/message_parser.py
puck_bridge_py/server.py
puck_bridge_py/utilities.py
puck_bridge_py-0.2.3.dist-info/licenses/LICENSE
puck_bridge_py-0.2.3.dist-info/METADATA
puck_bridge_py-0.2.3.dist-info/WHEEL
puck_bridge_py-0.2.3.dist-info/entry_points.txt
puck_bridge_py-0.2.3.dist-info/top_level.txt
puck_bridge_py-0.2.3.dist-info/RECORD
