Metadata-Version: 2.4
Name: puck-bridge-py
Version: 0.2.3
Summary: Python library for connecting to and interacting with Puck servers
Author-email: sn0w12 <lucasskold49@gmail.com>
License: MIT
Project-URL: Homepage, https://github.com/sn0w12/puck-bridge-py
Project-URL: Repository, https://github.com/sn0w12/puck-bridge-py
Project-URL: Issues, https://github.com/sn0w12/puck-bridge-py/issues
Keywords: puck,hockey,game,bridge,server,mod
Classifier: Development Status :: 4 - Beta
Classifier: Intended Audience :: Developers
Classifier: License :: OSI Approved :: MIT License
Classifier: Programming Language :: Python :: 3
Classifier: Programming Language :: Python :: 3.7
Classifier: Programming Language :: Python :: 3.8
Classifier: Programming Language :: Python :: 3.9
Classifier: Programming Language :: Python :: 3.10
Classifier: Programming Language :: Python :: 3.11
Classifier: Programming Language :: Python :: 3.12
Classifier: Topic :: Games/Entertainment
Classifier: Topic :: Software Development :: Libraries :: Python Modules
Requires-Python: >=3.7
License-File: LICENSE
Dynamic: license-file
